{
  "project_info": {
    "project_number": "630788660119",
    "project_id": "supplicationsapp-c3092",
    "storage_bucket": "supplicationsapp-c3092.appspot.com"
  },
  "client": [
    {
      "client_info": {
        "mobilesdk_app_id": "1:630788660119:android:e7b3a049910dd4199ec2d2",
        "android_client_info": {
          "package_name": "com.example.daily_supplications_app"
        }
      },
      "oauth_client": [],
      "api_key": [
        {
          "current_key": "AIzaSyDMAyXgLFcVOT7ziKtX5TbD2rYhqHFVOaY"
        }
      ],
      "services": {
        "appinvite_service": {
          "other_platform_oauth_client": []
        }
      }
    }
  ],
  "configuration_version": "1"
}